copili/__init__.py
copili/container_manager.py
copili/registry.py
copili-1.4.1.dist-info/LICENSE.md
copili-1.4.1.dist-info/METADATA
copili-1.4.1.dist-info/WHEEL
copili-1.4.1.dist-info/top_level.txt
copili-1.4.1.dist-info/RECORD
