Metadata-Version: 2.1
Name: copili
Version: 1.4.1
Summary: Run a series of docker/podman containers, in a coordinated manner
Home-page: https://git.connect.dzd-ev.de/dzdpythonmodules/copili
Author: TB
Author-email: tim.bleimehl@helmholtz-muenchen.de
License: MIT
Requires-Python: >=3.6
License-File: LICENSE.md
Requires-Dist: linetimer
Requires-Dist: docker
Requires-Dist: schedule
Requires-Dist: pyyaml
Requires-Dist: python-dotenv
Requires-Dist: expandvars
